Metadata-Version: 2.1
Name: cayenne
Version: 1.0.2
Summary: Python package for stochastic simulations
Home-page: https://github.com/Heuro-labs/cayenne
Author: Dileep Kishore, Srikiran Chandrasekaran
Author-email: k.dileep1994@gmail.com
License: Apache Software License 2.0
Keywords: cayenne stochastic gillepsie simulation
Platform: UNKNOWN
Classifier: Development Status :: 5 - Production/Stable
Classifier: Intended Audience :: Developers
Classifier: Intended Audience :: Science/Research
Classifier: License :: OSI Approved :: Apache Software License
Classifier: Natural Language :: English
Classifier: Programming Language :: Python :: 3.6
Classifier: Programming Language :: Python :: 3.7
